cloudos_cli/__init__.py
cloudos_cli/__main__.py
cloudos_cli/_version.py
cloudos_cli/clos.py
cloudos_cli/configure/__init__.py
cloudos_cli/configure/configure.py
cloudos_cli/cost/__init__.py
cloudos_cli/cost/cost.py
cloudos_cli/datasets/__init__.py
cloudos_cli/datasets/datasets.py
cloudos_cli/import_wf/__init__.py
cloudos_cli/import_wf/import_wf.py
cloudos_cli/jobs/__init__.py
cloudos_cli/jobs/job.py
cloudos_cli/link/__init__.py
cloudos_cli/link/link.py
cloudos_cli/logging/__init__.py
cloudos_cli/logging/logger.py
cloudos_cli/procurement/__init__.py
cloudos_cli/procurement/images.py
cloudos_cli/queue/__init__.py
cloudos_cli/queue/queue.py
cloudos_cli/related_analyses/__init__.py
cloudos_cli/related_analyses/related_analyses.py
cloudos_cli/utils/__init__.py
cloudos_cli/utils/array_job.py
cloudos_cli/utils/cloud.py
cloudos_cli/utils/details.py
cloudos_cli/utils/errors.py
cloudos_cli/utils/last_wf.py
cloudos_cli/utils/requests.py
cloudos_cli/utils/resources.py
cloudos_cli-2.78.0.dist-info/licenses/LICENSE
tests/__init__.py
tests/functions_for_pytest.py
tests/test_cli_project_create.py
tests/test_error_messages.py
tests/test_cost/__init__.py
tests/test_cost/test_job_cost.py
tests/test_logging/__init__.py
tests/test_logging/test_logger.py
tests/test_related_analyses/__init__.py
tests/test_related_analyses/test_related_analyses.py
cloudos_cli-2.78.0.dist-info/METADATA
cloudos_cli-2.78.0.dist-info/WHEEL
cloudos_cli-2.78.0.dist-info/entry_points.txt
cloudos_cli-2.78.0.dist-info/top_level.txt
cloudos_cli-2.78.0.dist-info/RECORD
