Metadata-Version: 2.4
Name: cloudos_cli
Version: 2.78.0
Summary: Python package for interacting with CloudOS
Home-page: https://github.com/lifebit-ai/cloudos-cli
Author: David Piñeyro
Author-email: david.pineyro@lifebit.ai
Classifier: Programming Language :: Python :: 3
Classifier: Operating System :: POSIX :: Linux
Classifier: License :: OSI Approved :: GNU General Public License v3 or later (GPLv3+)
Requires-Python: >=3.9
License-File: LICENSE
Requires-Dist: click>=8.0.1
Requires-Dist: rich-click>=1.8.2
Requires-Dist: pandas>=1.3.4
Requires-Dist: numpy>=1.26.4
Requires-Dist: requests>=2.26.0
Provides-Extra: test
Requires-Dist: pytest; extra == "test"
Requires-Dist: mock; extra == "test"
Requires-Dist: responses; extra == "test"
Requires-Dist: requests_mock; extra == "test"
Dynamic: author
Dynamic: author-email
Dynamic: classifier
Dynamic: description
Dynamic: description-content-type
Dynamic: home-page
Dynamic: license-file
Dynamic: provides-extra
Dynamic: requires-dist
Dynamic: requires-python
Dynamic: summary
